blivedm/__init__.py
blivedm/handlers.py
blivedm/utils.py
blivedm/clients/__init__.py
blivedm/clients/open_live.py
blivedm/clients/web.py
blivedm/clients/ws_base.py
blivedm/models/__init__.py
blivedm/models/open_live.py
blivedm/models/web.py
sumiblivedm/__init__.py
sumiblivedm/handlers.py
sumiblivedm/utils.py
sumiblivedm/clients/__init__.py
sumiblivedm/clients/open_live.py
sumiblivedm/clients/web.py
sumiblivedm/clients/ws_base.py
sumiblivedm/models/__init__.py
sumiblivedm/models/open_live.py
sumiblivedm/models/web.py
sumiblivedm-1.1.0.dist-info/LICENSE
sumiblivedm-1.1.0.dist-info/METADATA
sumiblivedm-1.1.0.dist-info/WHEEL
sumiblivedm-1.1.0.dist-info/top_level.txt
sumiblivedm-1.1.0.dist-info/RECORD
