Metadata-Version: 2.1
Name: sumiblivedm
Version: 1.1.0
Summary: 哔哩哔哩的开放平台（直播）链接模块
Home-page: https://github.com/15906617886/blivedm
Author: sumi
Author-email: 
License: Apache2
Keywords: bilibili openclient
Classifier: Development Status :: 5 - Production/Stable
Classifier: Intended Audience :: Developers
Classifier: Topic :: System :: Logging
Classifier: Topic :: Software Development :: Libraries
Classifier: Topic :: Internet :: Log Analysis
Classifier: License :: OSI Approved :: Apache Software License
Classifier: Programming Language :: Python :: 3.8
Requires-Python: >=3.8
License-File: LICENSE
Requires-Dist: aiohttp ~=3.9.0
Requires-Dist: Brotli ~=1.1.0
Requires-Dist: yarl ~=1.9.3
Provides-Extra: dev
Requires-Dist: check-manifest ; extra == 'dev'
Requires-Dist: six ; extra == 'dev'
Requires-Dist: pylint ; extra == 'dev'
Provides-Extra: test
Requires-Dist: coverage ; extra == 'test'
